{
    "pages": [
        "Halfwidth_and_Fullwidth_Forms.png"
    ],
    "chars": [
        {
            "id": 65343,
            "index": 33031,
            "char": "＿",
            "width": 40,
            "height": 10,
            "xoffset": -4,
            "yoffset": 32,
            "xadvance": 32,
            "chnl": 15,
            "x": 0,
            "y": 0,
            "page": 0
        },
        {
            "id": 65354,
            "index": 33042,
            "char": "ｊ",
            "width": 19,
            "height": 40,
            "xoffset": 4,
            "yoffset": 5,
            "xadvance": 32,
            "chnl": 15,
            "x": 0,
            "y": 12,
            "page": 0
        },
        {
            "id": 65372,
            "index": 33060,
            "char": "｜",
            "width": 10,
            "height": 40,
            "xoffset": 11,
            "yoffset": 5,
            "xadvance": 32,
            "chnl": 15,
            "x": 21,
            "y": 12,
            "page": 0
        },
        {
            "id": 65508,
            "index": 33130,
            "char": "￤",
            "width": 10,
            "height": 40,
            "xoffset": 11,
            "yoffset": 5,
            "xadvance": 32,
            "chnl": 15,
            "x": 33,
            "y": 12,
            "page": 0
        },
        {
            "id": 65329,
            "index": 33017,
            "char": "Ｑ",
            "width": 29,
            "height": 38,
            "xoffset": 2,
            "yoffset": 6,
            "xadvance": 32,
            "chnl": 15,
            "x": 45,
            "y": 0,
            "page": 0
        },
        {
            "id": 65510,
            "index": 79,
            "char": "￦",
            "width": 38,
            "height": 31,
            "xoffset": -3,
            "yoffset": 6,
            "xadvance": 32,
            "chnl": 15,
            "x": 45,
            "y": 40,
            "page": 0
        },
        {
            "id": 65288,
            "index": 32976,
            "char": "（",
            "width": 19,
            "height": 36,
            "xoffset": 8,
            "yoffset": 6,
            "xadvance": 32,
            "chnl": 15,
            "x": 85,
            "y": 0,
            "page": 0
        },
        {
            "id": 65289,
            "index": 32977,
            "char": "）",
            "width": 19,
            "height": 36,
            "xoffset": 5,
            "yoffset": 6,
            "xadvance": 32,
            "chnl": 15,
            "x": 85,
            "y": 38,
            "page": 0
        },
        {
            "id": 65335,
            "index": 33023,
            "char": "Ｗ",
            "width": 36,
            "height": 31,
            "xoffset": -2,
            "yoffset": 6,
            "xadvance": 32,
            "chnl": 15,
            "x": 0,
            "y": 54,
            "page": 0
        },
        {
            "id": 65339,
            "index": 33027,
            "char": "［",
            "width": 17,
            "height": 36,
            "xoffset": 9,
            "yoffset": 6,
            "xadvance": 32,
            "chnl": 15,
            "x": 0,
            "y": 87,
            "page": 0
        },
        {
            "id": 65341,
            "index": 33029,
            "char": "］",
            "width": 17,
            "height": 36,
            "xoffset": 6,
            "yoffset": 6,
            "xadvance": 32,
            "chnl": 15,
            "x": 19,
            "y": 87,
            "page": 0
        },
        {
            "id": 65371,
            "index": 33059,
            "char": "｛",
            "width": 22,
            "height": 36,
            "xoffset": 6,
            "yoffset": 6,
            "xadvance": 32,
            "chnl": 15,
            "x": 38,
            "y": 76,
            "page": 0
        },
        {
            "id": 65373,
            "index": 33061,
            "char": "｝",
            "width": 22,
            "height": 36,
            "xoffset": 5,
            "yoffset": 6,
            "xadvance": 32,
            "chnl": 15,
            "x": 62,
            "y": 76,
            "page": 0
        },
        {
            "id": 65395,
            "index": 33081,
            "char": "ｳ",
            "width": 20,
            "height": 35,
            "xoffset": -2,
            "yoffset": 4,
            "xadvance": 16,
            "chnl": 15,
            "x": 106,
            "y": 0,
            "page": 0
        },
        {
            "id": 65399,
            "index": 33085,
            "char": "ｷ",
            "width": 22,
            "height": 35,
            "xoffset": -3,
            "yoffset": 4,
            "xadvance": 16,
            "chnl": 15,
            "x": 86,
            "y": 76,
            "page": 0
        },
        {
            "id": 65400,
            "index": 33086,
            "char": "ｸ",
            "width": 22,
            "height": 35,
            "xoffset": -3,
            "yoffset": 4,
            "xadvance": 16,
            "chnl": 15,
            "x": 0,
            "y": 125,
            "page": 0
        },
        {
            "id": 65401,
            "index": 33087,
            "char": "ｹ",
            "width": 23,
            "height": 35,
            "xoffset": -3,
            "yoffset": 4,
            "xadvance": 16,
            "chnl": 15,
            "x": 24,
            "y": 125,
            "page": 0
        },
        {
            "id": 65408,
            "index": 33094,
            "char": "ﾀ",
            "width": 23,
            "height": 35,
            "xoffset": -3,
            "yoffset": 4,
            "xadvance": 16,
            "chnl": 15,
            "x": 49,
            "y": 114,
            "page": 0
        },
        {
            "id": 65412,
            "index": 33098,
            "char": "ﾄ",
            "width": 19,
            "height": 35,
            "xoffset": 1,
            "yoffset": 4,
            "xadvance": 16,
            "chnl": 15,
            "x": 106,
            "y": 37,
            "page": 0
        },
        {
            "id": 65416,
            "index": 33102,
            "char": "ﾈ",
            "width": 24,
            "height": 35,
            "xoffset": -4,
            "yoffset": 4,
            "xadvance": 16,
            "chnl": 15,
            "x": 74,
            "y": 114,
            "page": 0
        },
        {
            "id": 65425,
            "index": 33111,
            "char": "ﾑ",
            "width": 23,
            "height": 35,
            "xoffset": -3,
            "yoffset": 5,
            "xadvance": 16,
            "chnl": 15,
            "x": 100,
            "y": 113,
            "page": 0
        },
        {
            "id": 65428,
            "index": 33114,
            "char": "ﾔ",
            "width": 23,
            "height": 35,
            "xoffset": -3,
            "yoffset": 4,
            "xadvance": 16,
            "chnl": 15,
            "x": 128,
            "y": 0,
            "page": 0
        },
        {
            "id": 65284,
            "index": 32972,
            "char": "＄",
            "width": 22,
            "height": 34,
            "xoffset": 5,
            "yoffset": 5,
            "xadvance": 32,
            "chnl": 15,
            "x": 127,
            "y": 37,
            "page": 0
        },
        {
            "id": 65312,
            "index": 33000,
            "char": "＠",
            "width": 32,
            "height": 34,
            "xoffset": 0,
            "yoffset": 6,
            "xadvance": 32,
            "chnl": 15,
            "x": 110,
            "y": 74,
            "page": 0
        },
        {
            "id": 65394,
            "index": 33080,
            "char": "ｲ",
            "width": 23,
            "height": 34,
            "xoffset": -3,
            "yoffset": 4,
            "xadvance": 16,
            "chnl": 15,
            "x": 125,
            "y": 110,
            "page": 0
        },
        {
            "id": 65397,
            "index": 33083,
            "char": "ｵ",
            "width": 22,
            "height": 34,
            "xoffset": -3,
            "yoffset": 4,
            "xadvance": 16,
            "chnl": 15,
            "x": 153,
            "y": 0,
            "page": 0
        },
        {
            "id": 65398,
            "index": 33084,
            "char": "ｶ",
            "width": 22,
            "height": 34,
            "xoffset": -3,
            "yoffset": 4,
            "xadvance": 16,
            "chnl": 15,
            "x": 153,
            "y": 36,
            "page": 0
        },
        {
            "id": 65403,
            "index": 33089,
            "char": "ｻ",
            "width": 23,
            "height": 34,
            "xoffset": -3,
            "yoffset": 5,
            "xadvance": 16,
            "chnl": 15,
            "x": 144,
            "y": 73,
            "page": 0
        },
        {
            "id": 65404,
            "index": 33090,
            "char": "ｼ",
            "width": 22,
            "height": 34,
            "xoffset": -3,
            "yoffset": 5,
            "xadvance": 16,
            "chnl": 15,
            "x": 150,
            "y": 109,
            "page": 0
        },
        {
            "id": 65406,
            "index": 33092,
            "char": "ｾ",
            "width": 23,
            "height": 34,
            "xoffset": -3,
            "yoffset": 4,
            "xadvance": 16,
            "chnl": 15,
            "x": 0,
            "y": 162,
            "page": 0
        },
        {
            "id": 65407,
            "index": 33093,
            "char": "ｿ",
            "width": 23,
            "height": 34,
            "xoffset": -3,
            "yoffset": 5,
            "xadvance": 16,
            "chnl": 15,
            "x": 25,
            "y": 162,
            "page": 0
        },
        {
            "id": 65409,
            "index": 33095,
            "char": "ﾁ",
            "width": 22,
            "height": 34,
            "xoffset": -3,
            "yoffset": 5,
            "xadvance": 16,
            "chnl": 15,
            "x": 150,
            "y": 145,
            "page": 0
        },
        {
            "id": 65413,
            "index": 33099,
            "char": "ﾅ",
            "width": 23,
            "height": 34,
            "xoffset": -3,
            "yoffset": 4,
            "xadvance": 16,
            "chnl": 15,
            "x": 125,
            "y": 146,
            "page": 0
        },
        {
            "id": 65417,
            "index": 33103,
            "char": "ﾉ",
            "width": 20,
            "height": 34,
            "xoffset": -2,
            "yoffset": 5,
            "xadvance": 16,
            "chnl": 15,
            "x": 100,
            "y": 150,
            "page": 0
        },
        {
            "id": 65418,
            "index": 33104,
            "char": "ﾊ",
            "width": 23,
            "height": 34,
            "xoffset": -3,
            "yoffset": 6,
            "xadvance": 16,
            "chnl": 15,
            "x": 50,
            "y": 151,
            "page": 0
        },
        {
            "id": 65422,
            "index": 33108,
            "char": "ﾎ",
            "width": 23,
            "height": 34,
            "xoffset": -3,
            "yoffset": 4,
            "xadvance": 16,
            "chnl": 15,
            "x": 75,
            "y": 151,
            "page": 0
        },
        {
            "id": 65424,
            "index": 33110,
            "char": "ﾐ",
            "width": 21,
            "height": 34,
            "xoffset": -2,
            "yoffset": 5,
            "xadvance": 16,
            "chnl": 15,
            "x": 177,
            "y": 0,
            "page": 0
        },
        {
            "id": 65426,
            "index": 33112,
            "char": "ﾒ",
            "width": 23,
            "height": 34,
            "xoffset": -3,
            "yoffset": 5,
            "xadvance": 16,
            "chnl": 15,
            "x": 169,
            "y": 72,
            "page": 0
        },
        {
            "id": 65432,
            "index": 33118,
            "char": "ﾘ",
            "width": 19,
            "height": 34,
            "xoffset": -1,
            "yoffset": 5,
            "xadvance": 16,
            "chnl": 15,
            "x": 177,
            "y": 36,
            "page": 0
        },
        {
            "id": 65433,
            "index": 33119,
            "char": "ﾙ",
            "width": 24,
            "height": 34,
            "xoffset": -4,
            "yoffset": 5,
            "xadvance": 16,
            "chnl": 15,
            "x": 174,
            "y": 108,
            "page": 0
        },
        {
            "id": 65434,
            "index": 33120,
            "char": "ﾚ",
            "width": 21,
            "height": 34,
            "xoffset": -2,
            "yoffset": 5,
            "xadvance": 16,
            "chnl": 15,
            "x": 174,
            "y": 144,
            "page": 0
        },
        {
            "id": 65285,
            "index": 32973,
            "char": "％",
            "width": 33,
            "height": 31,
            "xoffset": 0,
            "yoffset": 6,
            "xadvance": 32,
            "chnl": 15,
            "x": 0,
            "y": 198,
            "page": 0
        },
        {
            "id": 65346,
            "index": 33034,
            "char": "ｂ",
            "width": 24,
            "height": 33,
            "xoffset": 5,
            "yoffset": 5,
            "xadvance": 32,
            "chnl": 15,
            "x": 174,
            "y": 180,
            "page": 0
        },
        {
            "id": 65348,
            "index": 33036,
            "char": "ｄ",
            "width": 24,
            "height": 33,
            "xoffset": 3,
            "yoffset": 5,
            "xadvance": 32,
            "chnl": 15,
            "x": 50,
            "y": 187,
            "page": 0
        },
        {
            "id": 65350,
            "index": 33038,
            "char": "ｆ",
            "width": 23,
            "height": 33,
            "xoffset": 4,
            "yoffset": 5,
            "xadvance": 32,
            "chnl": 15,
            "x": 76,
            "y": 187,
            "page": 0
        },
        {
            "id": 65351,
            "index": 33039,
            "char": "ｇ",
            "width": 25,
            "height": 33,
            "xoffset": 3,
            "yoffset": 12,
            "xadvance": 32,
            "chnl": 15,
            "x": 101,
            "y": 186,
            "page": 0
        },
        {
            "id": 65360,
            "index": 33048,
            "char": "ｐ",
            "width": 24,
            "height": 33,
            "xoffset": 5,
            "yoffset": 12,
            "xadvance": 32,
            "chnl": 15,
            "x": 128,
            "y": 182,
            "page": 0
        },
        {
            "id": 65361,
            "index": 33049,
            "char": "ｑ",
            "width": 24,
            "height": 33,
            "xoffset": 3,
            "yoffset": 12,
            "xadvance": 32,
            "chnl": 15,
            "x": 200,
            "y": 0,
            "page": 0
        },
        {
            "id": 65369,
            "index": 33057,
            "char": "ｙ",
            "width": 25,
            "height": 33,
            "xoffset": 3,
            "yoffset": 12,
            "xadvance": 32,
            "chnl": 15,
            "x": 194,
            "y": 72,
            "page": 0
        },
        {
            "id": 65382,
            "index": 33068,
            "char": "ｦ",
            "width": 20,
            "height": 33,
            "xoffset": -2,
            "yoffset": 6,
            "xadvance": 16,
            "chnl": 15,
            "x": 197,
            "y": 144,
            "page": 0
        },
        {
            "id": 65393,
            "index": 33079,
            "char": "ｱ",
            "width": 23,
            "height": 33,
            "xoffset": -3,
            "yoffset": 6,
            "xadvance": 16,
            "chnl": 15,
            "x": 198,
            "y": 36,
            "page": 0
        },
        {
            "id": 65405,
            "index": 33091,
            "char": "ｽ",
            "width": 23,
            "height": 33,
            "xoffset": -4,
            "yoffset": 6,
            "xadvance": 16,
            "chnl": 15,
            "x": 200,
            "y": 107,
            "page": 0
        },
        {
            "id": 65410,
            "index": 33096,
            "char": "ﾂ",
            "width": 23,
            "height": 33,
            "xoffset": -3,
            "yoffset": 6,
            "xadvance": 16,
            "chnl": 15,
            "x": 200,
            "y": 179,
            "page": 0
        },
        {
            "id": 65411,
            "index": 33097,
            "char": "ﾃ",
            "width": 22,
            "height": 33,
            "xoffset": -3,
            "yoffset": 6,
            "xadvance": 16,
            "chnl": 15,
            "x": 226,
            "y": 0,
            "page": 0
        },
        {
            "id": 65415,
            "index": 33101,
            "char": "ﾇ",
            "width": 22,
            "height": 33,
            "xoffset": -3,
            "yoffset": 6,
            "xadvance": 16,
            "chnl": 15,
            "x": 221,
            "y": 71,
            "page": 0
        },
        {
            "id": 65419,
            "index": 33105,
            "char": "ﾋ",
            "width": 20,
            "height": 33,
            "xoffset": -2,
            "yoffset": 5,
            "xadvance": 16,
            "chnl": 15,
            "x": 223,
            "y": 35,
            "page": 0
        },
        {
            "id": 65423,
            "index": 33109,
            "char": "ﾏ",
            "width": 22,
            "height": 33,
            "xoffset": -3,
            "yoffset": 6,
            "xadvance": 16,
            "chnl": 15,
            "x": 225,
            "y": 106,
            "page": 0
        },
        {
            "id": 65431,
            "index": 33117,
            "char": "ﾗ",
            "width": 21,
            "height": 33,
            "xoffset": -2,
            "yoffset": 6,
            "xadvance": 16,
            "chnl": 15,
            "x": 219,
            "y": 142,
            "page": 0
        },
        {
            "id": 65436,
            "index": 33122,
            "char": "ﾜ",
            "width": 21,
            "height": 33,
            "xoffset": -2,
            "yoffset": 6,
            "xadvance": 16,
            "chnl": 15,
            "x": 225,
            "y": 177,
            "page": 0
        },
        {
            "id": 65437,
            "index": 33123,
            "char": "ﾝ",
            "width": 23,
            "height": 33,
            "xoffset": -3,
            "yoffset": 6,
            "xadvance": 16,
            "chnl": 15,
            "x": 225,
            "y": 212,
            "page": 0
        },
        {
            "id": 65286,
            "index": 32974,
            "char": "＆",
            "width": 28,
            "height": 32,
            "xoffset": 3,
            "yoffset": 6,
            "xadvance": 32,
            "chnl": 15,
            "x": 0,
            "y": 231,
            "page": 0
        },
        {
            "id": 65296,
            "index": 32984,
            "char": "０",
            "width": 23,
            "height": 32,
            "xoffset": 5,
            "yoffset": 6,
            "xadvance": 32,
            "chnl": 15,
            "x": 200,
            "y": 214,
            "page": 0
        },
        {
            "id": 65304,
            "index": 32992,
            "char": "８",
            "width": 22,
            "height": 32,
            "xoffset": 5,
            "yoffset": 6,
            "xadvance": 32,
            "chnl": 15,
            "x": 30,
            "y": 231,
            "page": 0
        },
        {
            "id": 65311,
            "index": 32999,
            "char": "？",
            "width": 22,
            "height": 32,
            "xoffset": 5,
            "yoffset": 6,
            "xadvance": 32,
            "chnl": 15,
            "x": 54,
            "y": 222,
            "page": 0
        },
        {
            "id": 65327,
            "index": 33015,
            "char": "Ｏ",
            "width": 29,
            "height": 32,
            "xoffset": 2,
            "yoffset": 6,
            "xadvance": 32,
            "chnl": 15,
            "x": 78,
            "y": 222,
            "page": 0
        },
        {
            "id": 65352,
            "index": 33040,
            "char": "ｈ",
            "width": 23,
            "height": 32,
            "xoffset": 4,
            "yoffset": 5,
            "xadvance": 32,
            "chnl": 15,
            "x": 109,
            "y": 221,
            "page": 0
        },
        {
            "id": 65353,
            "index": 33041,
            "char": "ｉ",
            "width": 22,
            "height": 32,
            "xoffset": 5,
            "yoffset": 5,
            "xadvance": 32,
            "chnl": 15,
            "x": 134,
            "y": 217,
            "page": 0
        },
        {
            "id": 65355,
            "index": 33043,
            "char": "ｋ",
            "width": 23,
            "height": 32,
            "xoffset": 6,
            "yoffset": 5,
            "xadvance": 32,
            "chnl": 15,
            "x": 158,
            "y": 215,
            "page": 0
        },
        {
            "id": 65356,
            "index": 33044,
            "char": "ｌ",
            "width": 22,
            "height": 32,
            "xoffset": 5,
            "yoffset": 5,
            "xadvance": 32,
            "chnl": 15,
            "x": 250,
            "y": 0,
            "page": 0
        },
        {
            "id": 65357,
            "index": 33045,
            "char": "ｍ",
            "width": 32,
            "height": 26,
            "xoffset": 0,
            "yoffset": 12,
            "xadvance": 32,
            "chnl": 15,
            "x": 0,
            "y": 265,
            "page": 0
        },
        {
            "id": 65420,
            "index": 33106,
            "char": "ﾌ",
            "width": 22,
            "height": 32,
            "xoffset": -3,
            "yoffset": 7,
            "xadvance": 16,
            "chnl": 15,
            "x": 250,
            "y": 34,
            "page": 0
        },
        {
            "id": 65427,
            "index": 33113,
            "char": "ﾓ",
            "width": 21,
            "height": 32,
            "xoffset": -3,
            "yoffset": 6,
            "xadvance": 16,
            "chnl": 15,
            "x": 250,
            "y": 68,
            "page": 0
        },
        {
            "id": 65430,
            "index": 33116,
            "char": "ﾖ",
            "width": 20,
            "height": 32,
            "xoffset": -2,
            "yoffset": 7,
            "xadvance": 16,
            "chnl": 15,
            "x": 242,
            "y": 141,
            "page": 0
        },
        {
            "id": 65281,
            "index": 32969,
            "char": "！",
            "width": 12,
            "height": 31,
            "xoffset": 10,
            "yoffset": 6,
            "xadvance": 32,
            "chnl": 15,
            "x": 35,
            "y": 198,
            "page": 0
        },
        {
            "id": 65283,
            "index": 32971,
            "char": "＃",
            "width": 27,
            "height": 31,
            "xoffset": 3,
            "yoffset": 6,
            "xadvance": 32,
            "chnl": 15,
            "x": 54,
            "y": 256,
            "page": 0
        },
        {
            "id": 65295,
            "index": 32983,
            "char": "／",
            "width": 24,
            "height": 31,
            "xoffset": 4,
            "yoffset": 6,
            "xadvance": 32,
            "chnl": 15,
            "x": 248,
            "y": 175,
            "page": 0
        },
        {
            "id": 65297,
            "index": 32985,
            "char": "１",
            "width": 16,
            "height": 31,
            "xoffset": 6,
            "yoffset": 6,
            "xadvance": 32,
            "chnl": 15,
            "x": 154,
            "y": 181,
            "page": 0
        },
        {
            "id": 65298,
            "index": 32986,
            "char": "２",
            "width": 22,
            "height": 31,
            "xoffset": 5,
            "yoffset": 6,
            "xadvance": 32,
            "chnl": 15,
            "x": 250,
            "y": 208,
            "page": 0
        },
        {
            "id": 65299,
            "index": 32987,
            "char": "３",
            "width": 23,
            "height": 31,
            "xoffset": 5,
            "yoffset": 6,
            "xadvance": 32,
            "chnl": 15,
            "x": 249,
            "y": 102,
            "page": 0
        },
        {
            "id": 65300,
            "index": 32988,
            "char": "４",
            "width": 25,
            "height": 31,
            "xoffset": 4,
            "yoffset": 6,
            "xadvance": 32,
            "chnl": 15,
            "x": 83,
            "y": 256,
            "page": 0
        },
        {
            "id": 65301,
            "index": 32989,
            "char": "５",
            "width": 22,
            "height": 31,
            "xoffset": 5,
            "yoffset": 6,
            "xadvance": 32,
            "chnl": 15,
            "x": 250,
            "y": 241,
            "page": 0
        },
        {
            "id": 65302,
            "index": 32990,
            "char": "６",
            "width": 23,
            "height": 31,
            "xoffset": 5,
            "yoffset": 6,
            "xadvance": 32,
            "chnl": 15,
            "x": 225,
            "y": 247,
            "page": 0
        },
        {
            "id": 65303,
            "index": 32991,
            "char": "７",
            "width": 23,
            "height": 31,
            "xoffset": 5,
            "yoffset": 6,
            "xadvance": 32,
            "chnl": 15,
            "x": 110,
            "y": 255,
            "page": 0
        },
        {
            "id": 65305,
            "index": 32993,
            "char": "９",
            "width": 23,
            "height": 31,
            "xoffset": 5,
            "yoffset": 6,
            "xadvance": 32,
            "chnl": 15,
            "x": 135,
            "y": 251,
            "page": 0
        },
        {
            "id": 65313,
            "index": 33001,
            "char": "Ａ",
            "width": 29,
            "height": 31,
            "xoffset": 2,
            "yoffset": 6,
            "xadvance": 32,
            "chnl": 15,
            "x": 183,
            "y": 248,
            "page": 0
        },
        {
            "id": 65314,
            "index": 33002,
            "char": "Ｂ",
            "width": 24,
            "height": 31,
            "xoffset": 5,
            "yoffset": 6,
            "xadvance": 32,
            "chnl": 15,
            "x": 274,
            "y": 0,
            "page": 0
        },
        {
            "id": 65315,
            "index": 33003,
            "char": "Ｃ",
            "width": 26,
            "height": 31,
            "xoffset": 3,
            "yoffset": 6,
            "xadvance": 32,
            "chnl": 15,
            "x": 264,
            "y": 135,
            "page": 0
        },
        {
            "id": 65316,
            "index": 33004,
            "char": "Ｄ",
            "width": 26,
            "height": 31,
            "xoffset": 4,
            "yoffset": 6,
            "xadvance": 32,
            "chnl": 15,
            "x": 0,
            "y": 293,
            "page": 0
        },
        {
            "id": 65317,
            "index": 33005,
            "char": "Ｅ",
            "width": 23,
            "height": 31,
            "xoffset": 5,
            "yoffset": 6,
            "xadvance": 32,
            "chnl": 15,
            "x": 273,
            "y": 68,
            "page": 0
        },
        {
            "id": 65318,
            "index": 33006,
            "char": "Ｆ",
            "width": 23,
            "height": 31,
            "xoffset": 5,
            "yoffset": 6,
            "xadvance": 32,
            "chnl": 15,
            "x": 274,
            "y": 168,
            "page": 0
        },
        {
            "id": 65319,
            "index": 33007,
            "char": "Ｇ",
            "width": 27,
            "height": 31,
            "xoffset": 3,
            "yoffset": 6,
            "xadvance": 32,
            "chnl": 15,
            "x": 28,
            "y": 293,
            "page": 0
        },
        {
            "id": 65320,
            "index": 33008,
            "char": "Ｈ",
            "width": 26,
            "height": 31,
            "xoffset": 3,
            "yoffset": 6,
            "xadvance": 32,
            "chnl": 15,
            "x": 57,
            "y": 289,
            "page": 0
        },
        {
            "id": 65321,
            "index": 33009,
            "char": "Ｉ",
            "width": 23,
            "height": 31,
            "xoffset": 5,
            "yoffset": 6,
            "xadvance": 32,
            "chnl": 15,
            "x": 274,
            "y": 33,
            "page": 0
        },
        {
            "id": 65322,
            "index": 33010,
            "char": "Ｊ",
            "width": 21,
            "height": 31,
            "xoffset": 4,
            "yoffset": 6,
            "xadvance": 32,
            "chnl": 15,
            "x": 160,
            "y": 249,
            "page": 0
        },
        {
            "id": 65323,
            "index": 33011,
            "char": "Ｋ",
            "width": 25,
            "height": 31,
            "xoffset": 5,
            "yoffset": 6,
            "xadvance": 32,
            "chnl": 15,
            "x": 85,
            "y": 289,
            "page": 0
        },
        {
            "id": 65324,
            "index": 33012,
            "char": "Ｌ",
            "width": 22,
            "height": 31,
            "xoffset": 6,
            "yoffset": 6,
            "xadvance": 32,
            "chnl": 15,
            "x": 274,
            "y": 101,
            "page": 0
        },
        {
            "id": 65325,
            "index": 33013,
            "char": "Ｍ",
            "width": 30,
            "height": 31,
            "xoffset": 1,
            "yoffset": 6,
            "xadvance": 32,
            "chnl": 15,
            "x": 112,
            "y": 288,
            "page": 0
        },
        {
            "id": 65326,
            "index": 33014,
            "char": "Ｎ",
            "width": 27,
            "height": 31,
            "xoffset": 3,
            "yoffset": 6,
            "xadvance": 32,
            "chnl": 15,
            "x": 144,
            "y": 284,
            "page": 0
        },
        {
            "id": 65328,
            "index": 33016,
            "char": "Ｐ",
            "width": 24,
            "height": 31,
            "xoffset": 5,
            "yoffset": 6,
            "xadvance": 32,
            "chnl": 15,
            "x": 274,
            "y": 201,
            "page": 0
        },
        {
            "id": 65330,
            "index": 33018,
            "char": "Ｒ",
            "width": 25,
            "height": 31,
            "xoffset": 4,
            "yoffset": 6,
            "xadvance": 32,
            "chnl": 15,
            "x": 173,
            "y": 282,
            "page": 0
        },
        {
            "id": 65331,
            "index": 33019,
            "char": "Ｓ",
            "width": 24,
            "height": 31,
            "xoffset": 4,
            "yoffset": 6,
            "xadvance": 32,
            "chnl": 15,
            "x": 274,
            "y": 234,
            "page": 0
        },
        {
            "id": 65332,
            "index": 33020,
            "char": "Ｔ",
            "width": 27,
            "height": 31,
            "xoffset": 2,
            "yoffset": 6,
            "xadvance": 32,
            "chnl": 15,
            "x": 200,
            "y": 281,
            "page": 0
        },
        {
            "id": 65333,
            "index": 33021,
            "char": "Ｕ",
            "width": 27,
            "height": 31,
            "xoffset": 3,
            "yoffset": 6,
            "xadvance": 32,
            "chnl": 15,
            "x": 229,
            "y": 280,
            "page": 0
        },
        {
            "id": 65334,
            "index": 33022,
            "char": "Ｖ",
            "width": 29,
            "height": 31,
            "xoffset": 2,
            "yoffset": 6,
            "xadvance": 32,
            "chnl": 15,
            "x": 258,
            "y": 274,
            "page": 0
        },
        {
            "id": 65336,
            "index": 33024,
            "char": "Ｘ",
            "width": 28,
            "height": 31,
            "xoffset": 2,
            "yoffset": 6,
            "xadvance": 32,
            "chnl": 15,
            "x": 300,
            "y": 0,
            "page": 0
        },
        {
            "id": 65337,
            "index": 33025,
            "char": "Ｙ",
            "width": 28,
            "height": 31,
            "xoffset": 2,
            "yoffset": 6,
            "xadvance": 32,
            "chnl": 15,
            "x": 300,
            "y": 33,
            "page": 0
        },
        {
            "id": 65338,
            "index": 33026,
            "char": "Ｚ",
            "width": 25,
            "height": 31,
            "xoffset": 3,
            "yoffset": 6,
            "xadvance": 32,
            "chnl": 15,
            "x": 292,
            "y": 134,
            "page": 0
        },
        {
            "id": 65340,
            "index": 33028,
            "char": "＼",
            "width": 24,
            "height": 31,
            "xoffset": 4,
            "yoffset": 6,
            "xadvance": 32,
            "chnl": 15,
            "x": 299,
            "y": 167,
            "page": 0
        },
        {
            "id": 65367,
            "index": 33055,
            "char": "ｗ",
            "width": 31,
            "height": 25,
            "xoffset": 0,
            "yoffset": 12,
            "xadvance": 32,
            "chnl": 15,
            "x": 289,
            "y": 267,
            "page": 0
        },
        {
            "id": 65384,
            "index": 33070,
            "char": "ｨ",
            "width": 21,
            "height": 31,
            "xoffset": -2,
            "yoffset": 10,
            "xadvance": 16,
            "chnl": 15,
            "x": 289,
            "y": 294,
            "page": 0
        },
        {
            "id": 65385,
            "index": 33071,
            "char": "ｩ",
            "width": 19,
            "height": 31,
            "xoffset": -1,
            "yoffset": 10,
            "xadvance": 16,
            "chnl": 15,
            "x": 300,
            "y": 200,
            "page": 0
        },
        {
            "id": 65387,
            "index": 33073,
            "char": "ｫ",
            "width": 20,
            "height": 31,
            "xoffset": -2,
            "yoffset": 10,
            "xadvance": 16,
            "chnl": 15,
            "x": 300,
            "y": 233,
            "page": 0
        },
        {
            "id": 65388,
            "index": 33074,
            "char": "ｬ",
            "width": 21,
            "height": 31,
            "xoffset": -2,
            "yoffset": 10,
            "xadvance": 16,
            "chnl": 15,
            "x": 298,
            "y": 66,
            "page": 0
        },
        {
            "id": 65435,
            "index": 33121,
            "char": "ﾛ",
            "width": 20,
            "height": 31,
            "xoffset": -2,
            "yoffset": 7,
            "xadvance": 16,
            "chnl": 15,
            "x": 298,
            "y": 99,
            "page": 0
        },
        {
            "id": 65504,
            "index": 33126,
            "char": "￠",
            "width": 20,
            "height": 31,
            "xoffset": 6,
            "yoffset": 6,
            "xadvance": 32,
            "chnl": 15,
            "x": 0,
            "y": 327,
            "page": 0
        },
        {
            "id": 65505,
            "index": 33127,
            "char": "￡",
            "width": 24,
            "height": 31,
            "xoffset": 4,
            "yoffset": 6,
            "xadvance": 32,
            "chnl": 15,
            "x": 22,
            "y": 327,
            "page": 0
        },
        {
            "id": 65507,
            "index": 33129,
            "char": "￣",
            "width": 31,
            "height": 10,
            "xoffset": 0,
            "yoffset": 3,
            "xadvance": 32,
            "chnl": 15,
            "x": 48,
            "y": 327,
            "page": 0
        },
        {
            "id": 65509,
            "index": 33131,
            "char": "￥",
            "width": 28,
            "height": 31,
            "xoffset": 2,
            "yoffset": 6,
            "xadvance": 32,
            "chnl": 15,
            "x": 81,
            "y": 327,
            "page": 0
        },
        {
            "id": 65307,
            "index": 32995,
            "char": "；",
            "width": 13,
            "height": 30,
            "xoffset": 9,
            "yoffset": 11,
            "xadvance": 32,
            "chnl": 15,
            "x": 183,
            "y": 215,
            "page": 0
        },
        {
            "id": 65364,
            "index": 33052,
            "char": "ｔ",
            "width": 22,
            "height": 30,
            "xoffset": 5,
            "yoffset": 7,
            "xadvance": 32,
            "chnl": 15,
            "x": 111,
            "y": 327,
            "page": 0
        },
        {
            "id": 65402,
            "index": 33088,
            "char": "ｺ",
            "width": 21,
            "height": 30,
            "xoffset": -2,
            "yoffset": 8,
            "xadvance": 16,
            "chnl": 15,
            "x": 135,
            "y": 327,
            "page": 0
        },
        {
            "id": 65383,
            "index": 33069,
            "char": "ｧ",
            "width": 21,
            "height": 29,
            "xoffset": -2,
            "yoffset": 11,
            "xadvance": 16,
            "chnl": 15,
            "x": 158,
            "y": 327,
            "page": 0
        },
        {
            "id": 65391,
            "index": 33077,
            "char": "ｯ",
            "width": 21,
            "height": 29,
            "xoffset": -2,
            "yoffset": 11,
            "xadvance": 16,
            "chnl": 15,
            "x": 181,
            "y": 327,
            "page": 0
        },
        {
            "id": 65414,
            "index": 33100,
            "char": "ﾆ",
            "width": 22,
            "height": 29,
            "xoffset": -3,
            "yoffset": 8,
            "xadvance": 16,
            "chnl": 15,
            "x": 204,
            "y": 327,
            "page": 0
        },
        {
            "id": 65421,
            "index": 33107,
            "char": "ﾍ",
            "width": 24,
            "height": 29,
            "xoffset": -4,
            "yoffset": 8,
            "xadvance": 16,
            "chnl": 15,
            "x": 228,
            "y": 327,
            "page": 0
        },
        {
            "id": 65429,
            "index": 33115,
            "char": "ﾕ",
            "width": 22,
            "height": 29,
            "xoffset": -3,
            "yoffset": 8,
            "xadvance": 16,
            "chnl": 15,
            "x": 254,
            "y": 327,
            "page": 0
        },
        {
            "id": 65390,
            "index": 33076,
            "char": "ｮ",
            "width": 18,
            "height": 28,
            "xoffset": -1,
            "yoffset": 12,
            "xadvance": 16,
            "chnl": 15,
            "x": 278,
            "y": 327,
            "page": 0
        },
        {
            "id": 65396,
            "index": 33082,
            "char": "ｴ",
            "width": 22,
            "height": 28,
            "xoffset": -3,
            "yoffset": 8,
            "xadvance": 16,
            "chnl": 15,
            "x": 298,
            "y": 327,
            "page": 0
        },
        {
            "id": 65290,
            "index": 32978,
            "char": "＊",
            "width": 26,
            "height": 23,
            "xoffset": 3,
            "yoffset": 5,
            "xadvance": 32,
            "chnl": 15,
            "x": 330,
            "y": 0,
            "page": 0
        },
        {
            "id": 65306,
            "index": 32994,
            "char": "：",
            "width": 12,
            "height": 26,
            "xoffset": 10,
            "yoffset": 11,
            "xadvance": 32,
            "chnl": 15,
            "x": 34,
            "y": 265,
            "page": 0
        },
        {
            "id": 65345,
            "index": 33033,
            "char": "ａ",
            "width": 23,
            "height": 26,
            "xoffset": 5,
            "yoffset": 12,
            "xadvance": 32,
            "chnl": 15,
            "x": 330,
            "y": 25,
            "page": 0
        },
        {
            "id": 65347,
            "index": 33035,
            "char": "ｃ",
            "width": 22,
            "height": 26,
            "xoffset": 5,
            "yoffset": 12,
            "xadvance": 32,
            "chnl": 15,
            "x": 330,
            "y": 53,
            "page": 0
        },
        {
            "id": 65349,
            "index": 33037,
            "char": "ｅ",
            "width": 24,
            "height": 26,
            "xoffset": 4,
            "yoffset": 12,
            "xadvance": 32,
            "chnl": 15,
            "x": 321,
            "y": 200,
            "page": 0
        },
        {
            "id": 65358,
            "index": 33046,
            "char": "ｎ",
            "width": 23,
            "height": 26,
            "xoffset": 4,
            "yoffset": 12,
            "xadvance": 32,
            "chnl": 15,
            "x": 312,
            "y": 294,
            "page": 0
        },
        {
            "id": 65359,
            "index": 33047,
            "char": "ｏ",
            "width": 24,
            "height": 26,
            "xoffset": 4,
            "yoffset": 12,
            "xadvance": 32,
            "chnl": 15,
            "x": 319,
            "y": 132,
            "page": 0
        },
        {
            "id": 65362,
            "index": 33050,
            "char": "ｒ",
            "width": 20,
            "height": 26,
            "xoffset": 6,
            "yoffset": 12,
            "xadvance": 32,
            "chnl": 15,
            "x": 320,
            "y": 99,
            "page": 0
        },
        {
            "id": 65363,
            "index": 33051,
            "char": "ｓ",
            "width": 21,
            "height": 26,
            "xoffset": 6,
            "yoffset": 12,
            "xadvance": 32,
            "chnl": 15,
            "x": 322,
            "y": 322,
            "page": 0
        },
        {
            "id": 65366,
            "index": 33054,
            "char": "ｖ",
            "width": 26,
            "height": 25,
            "xoffset": 3,
            "yoffset": 12,
            "xadvance": 32,
            "chnl": 15,
            "x": 325,
            "y": 160,
            "page": 0
        },
        {
            "id": 65368,
            "index": 33056,
            "char": "ｘ",
            "width": 26,
            "height": 25,
            "xoffset": 3,
            "yoffset": 12,
            "xadvance": 32,
            "chnl": 15,
            "x": 322,
            "y": 228,
            "page": 0
        },
        {
            "id": 65378,
            "index": 33064,
            "char": "｢",
            "width": 17,
            "height": 26,
            "xoffset": 2,
            "yoffset": 4,
            "xadvance": 16,
            "chnl": 15,
            "x": 337,
            "y": 255,
            "page": 0
        },
        {
            "id": 65379,
            "index": 33065,
            "char": "｣",
            "width": 17,
            "height": 26,
            "xoffset": -3,
            "yoffset": 14,
            "xadvance": 16,
            "chnl": 15,
            "x": 337,
            "y": 283,
            "page": 0
        },
        {
            "id": 65308,
            "index": 32996,
            "char": "＜",
            "width": 23,
            "height": 25,
            "xoffset": 5,
            "yoffset": 10,
            "xadvance": 32,
            "chnl": 15,
            "x": 358,
            "y": 0,
            "page": 0
        },
        {
            "id": 65310,
            "index": 32998,
            "char": "＞",
            "width": 23,
            "height": 25,
            "xoffset": 5,
            "yoffset": 10,
            "xadvance": 32,
            "chnl": 15,
            "x": 356,
            "y": 27,
            "page": 0
        },
        {
            "id": 65365,
            "index": 33053,
            "char": "ｕ",
            "width": 23,
            "height": 25,
            "xoffset": 4,
            "yoffset": 12,
            "xadvance": 32,
            "chnl": 15,
            "x": 356,
            "y": 54,
            "page": 0
        },
        {
            "id": 65370,
            "index": 33058,
            "char": "ｚ",
            "width": 22,
            "height": 25,
            "xoffset": 5,
            "yoffset": 12,
            "xadvance": 32,
            "chnl": 15,
            "x": 356,
            "y": 81,
            "page": 0
        },
        {
            "id": 65386,
            "index": 33072,
            "char": "ｪ",
            "width": 20,
            "height": 25,
            "xoffset": -2,
            "yoffset": 14,
            "xadvance": 16,
            "chnl": 15,
            "x": 356,
            "y": 108,
            "page": 0
        },
        {
            "id": 65389,
            "index": 33075,
            "char": "ｭ",
            "width": 20,
            "height": 25,
            "xoffset": -2,
            "yoffset": 13,
            "xadvance": 16,
            "chnl": 15,
            "x": 356,
            "y": 135,
            "page": 0
        },
        {
            "id": 65342,
            "index": 33030,
            "char": "＾",
            "width": 24,
            "height": 22,
            "xoffset": 4,
            "yoffset": 6,
            "xadvance": 32,
            "chnl": 15,
            "x": 356,
            "y": 162,
            "page": 0
        },
        {
            "id": 65291,
            "index": 32979,
            "char": "＋",
            "width": 23,
            "height": 22,
            "xoffset": 5,
            "yoffset": 11,
            "xadvance": 32,
            "chnl": 15,
            "x": 356,
            "y": 186,
            "page": 0
        },
        {
            "id": 65309,
            "index": 32997,
            "char": "＝",
            "width": 23,
            "height": 17,
            "xoffset": 5,
            "yoffset": 13,
            "xadvance": 32,
            "chnl": 15,
            "x": 258,
            "y": 307,
            "page": 0
        },
        {
            "id": 65374,
            "index": 33062,
            "char": "～",
            "width": 23,
            "height": 12,
            "xoffset": 5,
            "yoffset": 16,
            "xadvance": 32,
            "chnl": 15,
            "x": 229,
            "y": 313,
            "page": 0
        },
        {
            "id": 65506,
            "index": 33128,
            "char": "￢",
            "width": 23,
            "height": 16,
            "xoffset": 5,
            "yoffset": 17,
            "xadvance": 32,
            "chnl": 15,
            "x": 321,
            "y": 81,
            "page": 0
        },
        {
            "id": 65392,
            "index": 33078,
            "char": "ｰ",
            "width": 21,
            "height": 11,
            "xoffset": -2,
            "yoffset": 16,
            "xadvance": 16,
            "chnl": 15,
            "x": 325,
            "y": 187,
            "page": 0
        },
        {
            "id": 65282,
            "index": 32970,
            "char": "＂",
            "width": 17,
            "height": 16,
            "xoffset": 8,
            "yoffset": 6,
            "xadvance": 32,
            "chnl": 15,
            "x": 347,
            "y": 210,
            "page": 0
        },
        {
            "id": 65377,
            "index": 33063,
            "char": "｡",
            "width": 17,
            "height": 17,
            "xoffset": -3,
            "yoffset": 24,
            "xadvance": 16,
            "chnl": 15,
            "x": 48,
            "y": 339,
            "page": 0
        },
        {
            "id": 65380,
            "index": 33066,
            "char": "､",
            "width": 16,
            "height": 17,
            "xoffset": -3,
            "yoffset": 24,
            "xadvance": 16,
            "chnl": 15,
            "x": 350,
            "y": 228,
            "page": 0
        },
        {
            "id": 65287,
            "index": 32975,
            "char": "＇",
            "width": 11,
            "height": 16,
            "xoffset": 11,
            "yoffset": 6,
            "xadvance": 32,
            "chnl": 15,
            "x": 366,
            "y": 210,
            "page": 0
        },
        {
            "id": 65292,
            "index": 32980,
            "char": "，",
            "width": 13,
            "height": 16,
            "xoffset": 10,
            "yoffset": 25,
            "xadvance": 32,
            "chnl": 15,
            "x": 322,
            "y": 255,
            "page": 0
        },
        {
            "id": 65293,
            "index": 32981,
            "char": "－",
            "width": 16,
            "height": 11,
            "xoffset": 8,
            "yoffset": 19,
            "xadvance": 32,
            "chnl": 15,
            "x": 200,
            "y": 314,
            "page": 0
        },
        {
            "id": 65344,
            "index": 33032,
            "char": "｀",
            "width": 14,
            "height": 13,
            "xoffset": 8,
            "yoffset": 5,
            "xadvance": 32,
            "chnl": 15,
            "x": 356,
            "y": 247,
            "page": 0
        },
        {
            "id": 65381,
            "index": 33067,
            "char": "･",
            "width": 14,
            "height": 14,
            "xoffset": -2,
            "yoffset": 15,
            "xadvance": 16,
            "chnl": 15,
            "x": 356,
            "y": 262,
            "page": 0
        },
        {
            "id": 65438,
            "index": 33124,
            "char": "ﾞ",
            "width": 14,
            "height": 14,
            "xoffset": -3,
            "yoffset": 2,
            "xadvance": 16,
            "chnl": 15,
            "x": 356,
            "y": 278,
            "page": 0
        },
        {
            "id": 65439,
            "index": 33125,
            "char": "ﾟ",
            "width": 14,
            "height": 14,
            "xoffset": -3,
            "yoffset": 2,
            "xadvance": 16,
            "chnl": 15,
            "x": 356,
            "y": 294,
            "page": 0
        },
        {
            "id": 65294,
            "index": 32982,
            "char": "．",
            "width": 12,
            "height": 12,
            "xoffset": 10,
            "yoffset": 25,
            "xadvance": 32,
            "chnl": 15,
            "x": 342,
            "y": 99,
            "page": 0
        }
    ],
    "info": {
        "face": "DroidSansFallback",
        "size": 32,
        "bold": 0,
        "italic": 0,
        "charset": [
            "！",
            "＂",
            "＃",
            "＄",
            "％",
            "＆",
            "＇",
            "（",
            "）",
            "＊",
            "＋",
            "，",
            "－",
            "．",
            "／",
            "０",
            "１",
            "２",
            "３",
            "４",
            "５",
            "６",
            "７",
            "８",
            "９",
            "：",
            "；",
            "＜",
            "＝",
            "＞",
            "？",
            "＠",
            "Ａ",
            "Ｂ",
            "Ｃ",
            "Ｄ",
            "Ｅ",
            "Ｆ",
            "Ｇ",
            "Ｈ",
            "Ｉ",
            "Ｊ",
            "Ｋ",
            "Ｌ",
            "Ｍ",
            "Ｎ",
            "Ｏ",
            "Ｐ",
            "Ｑ",
            "Ｒ",
            "Ｓ",
            "Ｔ",
            "Ｕ",
            "Ｖ",
            "Ｗ",
            "Ｘ",
            "Ｙ",
            "Ｚ",
            "［",
            "＼",
            "］",
            "＾",
            "＿",
            "｀",
            "ａ",
            "ｂ",
            "ｃ",
            "ｄ",
            "ｅ",
            "ｆ",
            "ｇ",
            "ｈ",
            "ｉ",
            "ｊ",
            "ｋ",
            "ｌ",
            "ｍ",
            "ｎ",
            "ｏ",
            "ｐ",
            "ｑ",
            "ｒ",
            "ｓ",
            "ｔ",
            "ｕ",
            "ｖ",
            "ｗ",
            "ｘ",
            "ｙ",
            "ｚ",
            "｛",
            "｜",
            "｝",
            "～",
            "｡",
            "｢",
            "｣",
            "､",
            "･",
            "ｦ",
            "ｧ",
            "ｨ",
            "ｩ",
            "ｪ",
            "ｫ",
            "ｬ",
            "ｭ",
            "ｮ",
            "ｯ",
            "ｰ",
            "ｱ",
            "ｲ",
            "ｳ",
            "ｴ",
            "ｵ",
            "ｶ",
            "ｷ",
            "ｸ",
            "ｹ",
            "ｺ",
            "ｻ",
            "ｼ",
            "ｽ",
            "ｾ",
            "ｿ",
            "ﾀ",
            "ﾁ",
            "ﾂ",
            "ﾃ",
            "ﾄ",
            "ﾅ",
            "ﾆ",
            "ﾇ",
            "ﾈ",
            "ﾉ",
            "ﾊ",
            "ﾋ",
            "ﾌ",
            "ﾍ",
            "ﾎ",
            "ﾏ",
            "ﾐ",
            "ﾑ",
            "ﾒ",
            "ﾓ",
            "ﾔ",
            "ﾕ",
            "ﾖ",
            "ﾗ",
            "ﾘ",
            "ﾙ",
            "ﾚ",
            "ﾛ",
            "ﾜ",
            "ﾝ",
            "ﾞ",
            "ﾟ",
            "￠",
            "￡",
            "￢",
            "￣",
            "￤",
            "￥",
            "￦"
        ],
        "unicode": 1,
        "stretchH": 100,
        "smooth": 1,
        "aa": 1,
        "padding": [
            4,
            4,
            4,
            4
        ],
        "spacing": [
            0,
            0
        ]
    },
    "common": {
        "lineHeight": 34,
        "base": 29,
        "scaleW": 381,
        "scaleH": 358,
        "pages": 1,
        "packed": 0,
        "alphaChnl": 0,
        "redChnl": 0,
        "greenChnl": 0,
        "blueChnl": 0
    },
    "distanceField": {
        "fieldType": "msdf",
        "distanceRange": 8
    },
    "kernings": []
}